[
    {
        "query_id": "740_93",
        "doc_id": "740_84",
        "score": 1
    },
    {
        "query_id": "740_787",
        "doc_id": "740_620",
        "score": 1
    },
    {
        "query_id": "740_897",
        "doc_id": "740_1294",
        "score": 1
    },
    {
        "query_id": "740_910",
        "doc_id": "740_5924",
        "score": 1
    },
    {
        "query_id": "740_620",
        "doc_id": "740_7695",
        "score": 1
    },
    {
        "query_id": "740_875",
        "doc_id": "740_7776",
        "score": 1
    },
    {
        "query_id": "740_692",
        "doc_id": "740_8726",
        "score": 1
    },
    {
        "query_id": "740_101",
        "doc_id": "740_10693",
        "score": 1
    },
    {
        "query_id": "740_534",
        "doc_id": "740_11128",
        "score": 1
    },
    {
        "query_id": "740_125",
        "doc_id": "740_11293",
        "score": 1
    },
    {
        "query_id": "740_630",
        "doc_id": "740_11308",
        "score": 1
    },
    {
        "query_id": "740_108",
        "doc_id": "740_11851",
        "score": 1
    },
    {
        "query_id": "740_138",
        "doc_id": "740_11895",
        "score": 1
    },
    {
        "query_id": "740_651",
        "doc_id": "740_14528",
        "score": 1
    },
    {
        "query_id": "740_49",
        "doc_id": "740_16392",
        "score": 1
    },
    {
        "query_id": "740_39",
        "doc_id": "740_16465",
        "score": 1
    },
    {
        "query_id": "740_160",
        "doc_id": "740_16742",
        "score": 1
    },
    {
        "query_id": "740_79",
        "doc_id": "740_16802",
        "score": 1
    },
    {
        "query_id": "740_484",
        "doc_id": "740_16809",
        "score": 1
    },
    {
        "query_id": "740_607",
        "doc_id": "740_16855",
        "score": 1
    },
    {
        "query_id": "740_89",
        "doc_id": "740_17012",
        "score": 1
    },
    {
        "query_id": "740_317",
        "doc_id": "740_17293",
        "score": 1
    },
    {
        "query_id": "740_224",
        "doc_id": "740_17342",
        "score": 1
    },
    {
        "query_id": "740_486",
        "doc_id": "740_17817",
        "score": 1
    },
    {
        "query_id": "740_904",
        "doc_id": "740_17923",
        "score": 1
    },
    {
        "query_id": "740_159",
        "doc_id": "740_18053",
        "score": 1
    },
    {
        "query_id": "740_848",
        "doc_id": "740_18075",
        "score": 1
    },
    {
        "query_id": "740_381",
        "doc_id": "740_18175",
        "score": 1
    },
    {
        "query_id": "740_592",
        "doc_id": "740_18264",
        "score": 1
    },
    {
        "query_id": "740_14",
        "doc_id": "740_18280",
        "score": 1
    },
    {
        "query_id": "740_520",
        "doc_id": "740_18612",
        "score": 1
    },
    {
        "query_id": "740_538",
        "doc_id": "740_19302",
        "score": 1
    },
    {
        "query_id": "740_468",
        "doc_id": "740_19684",
        "score": 1
    },
    {
        "query_id": "740_737",
        "doc_id": "740_19843",
        "score": 1
    },
    {
        "query_id": "740_216",
        "doc_id": "740_20076",
        "score": 1
    },
    {
        "query_id": "740_469",
        "doc_id": "740_20554",
        "score": 1
    },
    {
        "query_id": "740_262",
        "doc_id": "740_20751",
        "score": 1
    },
    {
        "query_id": "740_167",
        "doc_id": "740_20809",
        "score": 1
    },
    {
        "query_id": "740_161",
        "doc_id": "740_20834",
        "score": 1
    },
    {
        "query_id": "740_833",
        "doc_id": "740_21102",
        "score": 1
    },
    {
        "query_id": "740_604",
        "doc_id": "740_21221",
        "score": 1
    },
    {
        "query_id": "740_308",
        "doc_id": "740_21337",
        "score": 1
    },
    {
        "query_id": "740_117",
        "doc_id": "740_21654",
        "score": 1
    },
    {
        "query_id": "740_331",
        "doc_id": "740_21690",
        "score": 1
    },
    {
        "query_id": "740_132",
        "doc_id": "740_22100",
        "score": 1
    },
    {
        "query_id": "740_680",
        "doc_id": "740_22114",
        "score": 1
    },
    {
        "query_id": "740_239",
        "doc_id": "740_22517",
        "score": 1
    },
    {
        "query_id": "740_194",
        "doc_id": "740_22710",
        "score": 1
    },
    {
        "query_id": "740_646",
        "doc_id": "740_22836",
        "score": 1
    },
    {
        "query_id": "740_85",
        "doc_id": "740_23309",
        "score": 1
    },
    {
        "query_id": "740_847",
        "doc_id": "740_23557",
        "score": 1
    },
    {
        "query_id": "740_485",
        "doc_id": "740_23755",
        "score": 1
    },
    {
        "query_id": "740_342",
        "doc_id": "740_23846",
        "score": 1
    },
    {
        "query_id": "740_55",
        "doc_id": "740_24851",
        "score": 1
    },
    {
        "query_id": "740_218",
        "doc_id": "740_24913",
        "score": 1
    },
    {
        "query_id": "740_518",
        "doc_id": "740_24968",
        "score": 1
    },
    {
        "query_id": "740_463",
        "doc_id": "740_25100",
        "score": 1
    },
    {
        "query_id": "740_323",
        "doc_id": "740_25124",
        "score": 1
    },
    {
        "query_id": "740_701",
        "doc_id": "740_25249",
        "score": 1
    },
    {
        "query_id": "740_835",
        "doc_id": "740_25318",
        "score": 1
    },
    {
        "query_id": "740_688",
        "doc_id": "740_25375",
        "score": 1
    },
    {
        "query_id": "740_913",
        "doc_id": "740_25395",
        "score": 1
    },
    {
        "query_id": "740_245",
        "doc_id": "740_25825",
        "score": 1
    },
    {
        "query_id": "740_475",
        "doc_id": "740_25940",
        "score": 1
    },
    {
        "query_id": "740_238",
        "doc_id": "740_26658",
        "score": 1
    },
    {
        "query_id": "740_322",
        "doc_id": "740_27444",
        "score": 1
    },
    {
        "query_id": "740_765",
        "doc_id": "740_27752",
        "score": 1
    },
    {
        "query_id": "740_669",
        "doc_id": "740_27881",
        "score": 1
    },
    {
        "query_id": "740_923",
        "doc_id": "740_28231",
        "score": 1
    },
    {
        "query_id": "740_460",
        "doc_id": "740_28476",
        "score": 1
    },
    {
        "query_id": "740_587",
        "doc_id": "740_28593",
        "score": 1
    },
    {
        "query_id": "740_822",
        "doc_id": "740_28971",
        "score": 1
    },
    {
        "query_id": "740_830",
        "doc_id": "740_29335",
        "score": 1
    },
    {
        "query_id": "740_881",
        "doc_id": "740_29508",
        "score": 1
    },
    {
        "query_id": "740_47",
        "doc_id": "740_29534",
        "score": 1
    },
    {
        "query_id": "740_383",
        "doc_id": "740_29618",
        "score": 1
    },
    {
        "query_id": "740_427",
        "doc_id": "740_29850",
        "score": 1
    },
    {
        "query_id": "740_716",
        "doc_id": "740_30202",
        "score": 1
    },
    {
        "query_id": "740_884",
        "doc_id": "740_30661",
        "score": 1
    },
    {
        "query_id": "740_689",
        "doc_id": "740_30897",
        "score": 1
    },
    {
        "query_id": "740_280",
        "doc_id": "740_31154",
        "score": 1
    },
    {
        "query_id": "740_865",
        "doc_id": "740_31947",
        "score": 1
    },
    {
        "query_id": "740_399",
        "doc_id": "740_32108",
        "score": 1
    },
    {
        "query_id": "740_316",
        "doc_id": "740_32142",
        "score": 1
    },
    {
        "query_id": "740_98",
        "doc_id": "740_32163",
        "score": 1
    },
    {
        "query_id": "740_80",
        "doc_id": "740_32209",
        "score": 1
    },
    {
        "query_id": "740_812",
        "doc_id": "740_32257",
        "score": 1
    },
    {
        "query_id": "740_502",
        "doc_id": "740_32497",
        "score": 1
    },
    {
        "query_id": "740_637",
        "doc_id": "740_32614",
        "score": 1
    },
    {
        "query_id": "740_909",
        "doc_id": "740_32631",
        "score": 1
    },
    {
        "query_id": "740_573",
        "doc_id": "740_32655",
        "score": 1
    },
    {
        "query_id": "740_363",
        "doc_id": "740_32765",
        "score": 1
    },
    {
        "query_id": "740_243",
        "doc_id": "740_32893",
        "score": 1
    },
    {
        "query_id": "740_405",
        "doc_id": "740_33550",
        "score": 1
    },
    {
        "query_id": "740_329",
        "doc_id": "740_34285",
        "score": 1
    },
    {
        "query_id": "740_102",
        "doc_id": "740_34420",
        "score": 1
    },
    {
        "query_id": "740_34",
        "doc_id": "740_35343",
        "score": 1
    },
    {
        "query_id": "740_33",
        "doc_id": "740_35393",
        "score": 1
    },
    {
        "query_id": "740_846",
        "doc_id": "740_35510",
        "score": 1
    },
    {
        "query_id": "740_788",
        "doc_id": "740_35851",
        "score": 1
    },
    {
        "query_id": "740_174",
        "doc_id": "740_35909",
        "score": 1
    },
    {
        "query_id": "740_722",
        "doc_id": "740_36156",
        "score": 1
    },
    {
        "query_id": "740_432",
        "doc_id": "740_36314",
        "score": 1
    },
    {
        "query_id": "740_581",
        "doc_id": "740_36366",
        "score": 1
    },
    {
        "query_id": "740_373",
        "doc_id": "740_36437",
        "score": 1
    },
    {
        "query_id": "740_297",
        "doc_id": "740_36447",
        "score": 1
    },
    {
        "query_id": "740_24",
        "doc_id": "740_36512",
        "score": 1
    },
    {
        "query_id": "740_871",
        "doc_id": "740_36596",
        "score": 1
    },
    {
        "query_id": "740_168",
        "doc_id": "740_36698",
        "score": 1
    },
    {
        "query_id": "740_48",
        "doc_id": "740_36792",
        "score": 1
    },
    {
        "query_id": "740_310",
        "doc_id": "740_36868",
        "score": 1
    },
    {
        "query_id": "740_170",
        "doc_id": "740_36908",
        "score": 1
    },
    {
        "query_id": "740_911",
        "doc_id": "740_36990",
        "score": 1
    },
    {
        "query_id": "740_72",
        "doc_id": "740_37076",
        "score": 1
    },
    {
        "query_id": "740_908",
        "doc_id": "740_37094",
        "score": 1
    },
    {
        "query_id": "740_935",
        "doc_id": "740_37113",
        "score": 1
    },
    {
        "query_id": "740_891",
        "doc_id": "740_37152",
        "score": 1
    },
    {
        "query_id": "740_566",
        "doc_id": "740_37448",
        "score": 1
    },
    {
        "query_id": "740_555",
        "doc_id": "740_37760",
        "score": 1
    },
    {
        "query_id": "740_492",
        "doc_id": "740_37876",
        "score": 1
    },
    {
        "query_id": "740_531",
        "doc_id": "740_37916",
        "score": 1
    },
    {
        "query_id": "740_933",
        "doc_id": "740_38348",
        "score": 1
    },
    {
        "query_id": "740_690",
        "doc_id": "740_38412",
        "score": 1
    },
    {
        "query_id": "740_351",
        "doc_id": "740_39164",
        "score": 1
    },
    {
        "query_id": "740_826",
        "doc_id": "740_39166",
        "score": 1
    },
    {
        "query_id": "740_446",
        "doc_id": "740_39229",
        "score": 1
    },
    {
        "query_id": "740_594",
        "doc_id": "740_39503",
        "score": 1
    },
    {
        "query_id": "740_612",
        "doc_id": "740_39674",
        "score": 1
    },
    {
        "query_id": "740_183",
        "doc_id": "740_39794",
        "score": 1
    },
    {
        "query_id": "740_271",
        "doc_id": "740_39853",
        "score": 1
    },
    {
        "query_id": "740_882",
        "doc_id": "740_39950",
        "score": 1
    },
    {
        "query_id": "740_698",
        "doc_id": "740_40042",
        "score": 1
    },
    {
        "query_id": "740_51",
        "doc_id": "740_40096",
        "score": 1
    },
    {
        "query_id": "740_365",
        "doc_id": "740_40155",
        "score": 1
    },
    {
        "query_id": "740_263",
        "doc_id": "740_40314",
        "score": 1
    },
    {
        "query_id": "740_736",
        "doc_id": "740_40459",
        "score": 1
    },
    {
        "query_id": "740_113",
        "doc_id": "740_40521",
        "score": 1
    },
    {
        "query_id": "740_626",
        "doc_id": "740_40645",
        "score": 1
    },
    {
        "query_id": "740_187",
        "doc_id": "740_40704",
        "score": 1
    },
    {
        "query_id": "740_457",
        "doc_id": "740_40781",
        "score": 1
    },
    {
        "query_id": "740_278",
        "doc_id": "740_40784",
        "score": 1
    },
    {
        "query_id": "740_797",
        "doc_id": "740_40859",
        "score": 1
    },
    {
        "query_id": "740_282",
        "doc_id": "740_40863",
        "score": 1
    },
    {
        "query_id": "740_87",
        "doc_id": "740_40902",
        "score": 1
    },
    {
        "query_id": "740_252",
        "doc_id": "740_40996",
        "score": 1
    },
    {
        "query_id": "740_886",
        "doc_id": "740_41050",
        "score": 1
    },
    {
        "query_id": "740_510",
        "doc_id": "740_41296",
        "score": 1
    },
    {
        "query_id": "740_648",
        "doc_id": "740_42125",
        "score": 1
    },
    {
        "query_id": "740_8",
        "doc_id": "740_42156",
        "score": 1
    },
    {
        "query_id": "740_745",
        "doc_id": "740_42605",
        "score": 1
    },
    {
        "query_id": "740_929",
        "doc_id": "740_42727",
        "score": 1
    },
    {
        "query_id": "740_742",
        "doc_id": "740_42805",
        "score": 1
    },
    {
        "query_id": "740_207",
        "doc_id": "740_42826",
        "score": 1
    },
    {
        "query_id": "740_802",
        "doc_id": "740_42999",
        "score": 1
    },
    {
        "query_id": "740_738",
        "doc_id": "740_43380",
        "score": 1
    },
    {
        "query_id": "740_227",
        "doc_id": "740_43475",
        "score": 1
    },
    {
        "query_id": "740_622",
        "doc_id": "740_43535",
        "score": 1
    },
    {
        "query_id": "740_900",
        "doc_id": "740_43724",
        "score": 1
    },
    {
        "query_id": "740_21",
        "doc_id": "740_43741",
        "score": 1
    },
    {
        "query_id": "740_186",
        "doc_id": "740_43854",
        "score": 1
    },
    {
        "query_id": "740_442",
        "doc_id": "740_44277",
        "score": 1
    },
    {
        "query_id": "740_800",
        "doc_id": "740_44479",
        "score": 1
    },
    {
        "query_id": "740_712",
        "doc_id": "740_44645",
        "score": 1
    },
    {
        "query_id": "740_655",
        "doc_id": "740_44658",
        "score": 1
    },
    {
        "query_id": "740_453",
        "doc_id": "740_44794",
        "score": 1
    },
    {
        "query_id": "740_850",
        "doc_id": "740_45035",
        "score": 1
    },
    {
        "query_id": "740_552",
        "doc_id": "740_45147",
        "score": 1
    },
    {
        "query_id": "740_562",
        "doc_id": "740_45379",
        "score": 1
    },
    {
        "query_id": "740_702",
        "doc_id": "740_45514",
        "score": 1
    },
    {
        "query_id": "740_810",
        "doc_id": "740_45590",
        "score": 1
    },
    {
        "query_id": "740_863",
        "doc_id": "740_45673",
        "score": 1
    },
    {
        "query_id": "740_189",
        "doc_id": "740_45817",
        "score": 1
    },
    {
        "query_id": "740_876",
        "doc_id": "740_45943",
        "score": 1
    },
    {
        "query_id": "740_769",
        "doc_id": "740_46019",
        "score": 1
    },
    {
        "query_id": "740_124",
        "doc_id": "740_46100",
        "score": 1
    },
    {
        "query_id": "740_918",
        "doc_id": "740_46425",
        "score": 1
    },
    {
        "query_id": "740_219",
        "doc_id": "740_46489",
        "score": 1
    },
    {
        "query_id": "740_333",
        "doc_id": "740_46541",
        "score": 1
    },
    {
        "query_id": "740_114",
        "doc_id": "740_46577",
        "score": 1
    },
    {
        "query_id": "740_336",
        "doc_id": "740_46679",
        "score": 1
    },
    {
        "query_id": "740_300",
        "doc_id": "740_47117",
        "score": 1
    },
    {
        "query_id": "740_470",
        "doc_id": "740_47459",
        "score": 1
    },
    {
        "query_id": "740_334",
        "doc_id": "740_48082",
        "score": 1
    },
    {
        "query_id": "740_149",
        "doc_id": "740_48115",
        "score": 1
    },
    {
        "query_id": "740_880",
        "doc_id": "740_48134",
        "score": 1
    },
    {
        "query_id": "740_527",
        "doc_id": "740_48289",
        "score": 1
    },
    {
        "query_id": "740_610",
        "doc_id": "740_48353",
        "score": 1
    },
    {
        "query_id": "740_927",
        "doc_id": "740_48423",
        "score": 1
    },
    {
        "query_id": "740_921",
        "doc_id": "740_48446",
        "score": 1
    },
    {
        "query_id": "740_517",
        "doc_id": "740_48479",
        "score": 1
    },
    {
        "query_id": "740_244",
        "doc_id": "740_48540",
        "score": 1
    },
    {
        "query_id": "740_674",
        "doc_id": "740_48650",
        "score": 1
    },
    {
        "query_id": "740_195",
        "doc_id": "740_48651",
        "score": 1
    },
    {
        "query_id": "740_883",
        "doc_id": "740_48748",
        "score": 1
    },
    {
        "query_id": "740_213",
        "doc_id": "740_48825",
        "score": 1
    },
    {
        "query_id": "740_325",
        "doc_id": "740_48829",
        "score": 1
    },
    {
        "query_id": "740_367",
        "doc_id": "740_48848",
        "score": 1
    },
    {
        "query_id": "740_366",
        "doc_id": "740_48898",
        "score": 1
    },
    {
        "query_id": "740_472",
        "doc_id": "740_49042",
        "score": 1
    },
    {
        "query_id": "740_371",
        "doc_id": "740_49111",
        "score": 1
    },
    {
        "query_id": "740_123",
        "doc_id": "740_49284",
        "score": 1
    },
    {
        "query_id": "740_435",
        "doc_id": "740_49565",
        "score": 1
    },
    {
        "query_id": "740_708",
        "doc_id": "740_49733",
        "score": 1
    },
    {
        "query_id": "740_416",
        "doc_id": "740_49824",
        "score": 1
    },
    {
        "query_id": "740_761",
        "doc_id": "740_50012",
        "score": 1
    },
    {
        "query_id": "740_845",
        "doc_id": "740_50166",
        "score": 1
    },
    {
        "query_id": "740_640",
        "doc_id": "740_50176",
        "score": 1
    },
    {
        "query_id": "740_6",
        "doc_id": "740_50344",
        "score": 1
    },
    {
        "query_id": "740_420",
        "doc_id": "740_50391",
        "score": 1
    },
    {
        "query_id": "740_602",
        "doc_id": "740_50532",
        "score": 1
    },
    {
        "query_id": "740_731",
        "doc_id": "740_50590",
        "score": 1
    },
    {
        "query_id": "740_497",
        "doc_id": "740_50810",
        "score": 1
    },
    {
        "query_id": "740_508",
        "doc_id": "740_50944",
        "score": 1
    },
    {
        "query_id": "740_799",
        "doc_id": "740_51137",
        "score": 1
    },
    {
        "query_id": "740_107",
        "doc_id": "740_51219",
        "score": 1
    },
    {
        "query_id": "740_726",
        "doc_id": "740_51297",
        "score": 1
    },
    {
        "query_id": "740_372",
        "doc_id": "740_51516",
        "score": 1
    },
    {
        "query_id": "740_515",
        "doc_id": "740_51563",
        "score": 1
    },
    {
        "query_id": "740_804",
        "doc_id": "740_51585",
        "score": 1
    },
    {
        "query_id": "740_691",
        "doc_id": "740_51696",
        "score": 1
    },
    {
        "query_id": "740_45",
        "doc_id": "740_51812",
        "score": 1
    },
    {
        "query_id": "740_939",
        "doc_id": "740_52178",
        "score": 1
    },
    {
        "query_id": "740_313",
        "doc_id": "740_52241",
        "score": 1
    },
    {
        "query_id": "740_66",
        "doc_id": "740_52556",
        "score": 1
    },
    {
        "query_id": "740_385",
        "doc_id": "740_52632",
        "score": 1
    },
    {
        "query_id": "740_665",
        "doc_id": "740_52848",
        "score": 1
    },
    {
        "query_id": "740_936",
        "doc_id": "740_52889",
        "score": 1
    },
    {
        "query_id": "740_326",
        "doc_id": "740_53048",
        "score": 1
    },
    {
        "query_id": "740_678",
        "doc_id": "740_53179",
        "score": 1
    },
    {
        "query_id": "740_240",
        "doc_id": "740_53192",
        "score": 1
    },
    {
        "query_id": "740_467",
        "doc_id": "740_53252",
        "score": 1
    },
    {
        "query_id": "740_235",
        "doc_id": "740_53260",
        "score": 1
    },
    {
        "query_id": "740_94",
        "doc_id": "740_53265",
        "score": 1
    },
    {
        "query_id": "740_358",
        "doc_id": "740_53301",
        "score": 1
    },
    {
        "query_id": "740_232",
        "doc_id": "740_53533",
        "score": 1
    },
    {
        "query_id": "740_225",
        "doc_id": "740_53566",
        "score": 1
    },
    {
        "query_id": "740_129",
        "doc_id": "740_53601",
        "score": 1
    },
    {
        "query_id": "740_345",
        "doc_id": "740_53608",
        "score": 1
    },
    {
        "query_id": "740_559",
        "doc_id": "740_53691",
        "score": 1
    },
    {
        "query_id": "740_574",
        "doc_id": "740_53804",
        "score": 1
    },
    {
        "query_id": "740_210",
        "doc_id": "740_54336",
        "score": 1
    },
    {
        "query_id": "740_390",
        "doc_id": "740_54352",
        "score": 1
    },
    {
        "query_id": "740_70",
        "doc_id": "740_54891",
        "score": 1
    },
    {
        "query_id": "740_693",
        "doc_id": "740_55558",
        "score": 1
    },
    {
        "query_id": "740_471",
        "doc_id": "740_55758",
        "score": 1
    },
    {
        "query_id": "740_397",
        "doc_id": "740_55986",
        "score": 1
    },
    {
        "query_id": "740_301",
        "doc_id": "740_56367",
        "score": 1
    },
    {
        "query_id": "740_780",
        "doc_id": "740_56637",
        "score": 1
    },
    {
        "query_id": "740_483",
        "doc_id": "740_56666",
        "score": 1
    },
    {
        "query_id": "740_260",
        "doc_id": "740_56700",
        "score": 1
    },
    {
        "query_id": "740_52",
        "doc_id": "740_57280",
        "score": 1
    },
    {
        "query_id": "740_430",
        "doc_id": "740_57302",
        "score": 1
    },
    {
        "query_id": "740_682",
        "doc_id": "740_57378",
        "score": 1
    },
    {
        "query_id": "740_522",
        "doc_id": "740_57401",
        "score": 1
    },
    {
        "query_id": "740_145",
        "doc_id": "740_57569",
        "score": 1
    },
    {
        "query_id": "740_635",
        "doc_id": "740_57699",
        "score": 1
    },
    {
        "query_id": "740_90",
        "doc_id": "740_57878",
        "score": 1
    },
    {
        "query_id": "740_388",
        "doc_id": "740_58470",
        "score": 1
    },
    {
        "query_id": "740_289",
        "doc_id": "740_58471",
        "score": 1
    },
    {
        "query_id": "740_617",
        "doc_id": "740_59021",
        "score": 1
    },
    {
        "query_id": "740_393",
        "doc_id": "740_59566",
        "score": 1
    },
    {
        "query_id": "740_481",
        "doc_id": "740_59615",
        "score": 1
    },
    {
        "query_id": "740_894",
        "doc_id": "740_59975",
        "score": 1
    },
    {
        "query_id": "740_768",
        "doc_id": "740_59994",
        "score": 1
    },
    {
        "query_id": "740_878",
        "doc_id": "740_60230",
        "score": 1
    },
    {
        "query_id": "740_709",
        "doc_id": "740_60265",
        "score": 1
    },
    {
        "query_id": "740_133",
        "doc_id": "740_60333",
        "score": 1
    },
    {
        "query_id": "740_81",
        "doc_id": "740_60464",
        "score": 1
    },
    {
        "query_id": "740_312",
        "doc_id": "740_60497",
        "score": 1
    },
    {
        "query_id": "740_619",
        "doc_id": "740_60855",
        "score": 1
    },
    {
        "query_id": "740_281",
        "doc_id": "740_60864",
        "score": 1
    },
    {
        "query_id": "740_925",
        "doc_id": "740_61079",
        "score": 1
    },
    {
        "query_id": "740_25",
        "doc_id": "740_61360",
        "score": 1
    },
    {
        "query_id": "740_156",
        "doc_id": "740_61439",
        "score": 1
    },
    {
        "query_id": "740_650",
        "doc_id": "740_61452",
        "score": 1
    },
    {
        "query_id": "740_36",
        "doc_id": "740_61941",
        "score": 1
    },
    {
        "query_id": "740_163",
        "doc_id": "740_62136",
        "score": 1
    },
    {
        "query_id": "740_917",
        "doc_id": "740_62157",
        "score": 1
    },
    {
        "query_id": "740_96",
        "doc_id": "740_62488",
        "score": 1
    },
    {
        "query_id": "740_424",
        "doc_id": "740_62490",
        "score": 1
    },
    {
        "query_id": "740_841",
        "doc_id": "740_62550",
        "score": 1
    },
    {
        "query_id": "740_61",
        "doc_id": "740_62839",
        "score": 1
    },
    {
        "query_id": "740_465",
        "doc_id": "740_63204",
        "score": 1
    },
    {
        "query_id": "740_861",
        "doc_id": "740_63814",
        "score": 1
    },
    {
        "query_id": "740_751",
        "doc_id": "740_63828",
        "score": 1
    },
    {
        "query_id": "740_332",
        "doc_id": "740_63912",
        "score": 1
    },
    {
        "query_id": "740_411",
        "doc_id": "740_64044",
        "score": 1
    },
    {
        "query_id": "740_756",
        "doc_id": "740_64151",
        "score": 1
    },
    {
        "query_id": "740_173",
        "doc_id": "740_64280",
        "score": 1
    },
    {
        "query_id": "740_35",
        "doc_id": "740_64468",
        "score": 1
    },
    {
        "query_id": "740_284",
        "doc_id": "740_64521",
        "score": 1
    },
    {
        "query_id": "740_825",
        "doc_id": "740_64633",
        "score": 1
    },
    {
        "query_id": "740_764",
        "doc_id": "740_64687",
        "score": 1
    },
    {
        "query_id": "740_426",
        "doc_id": "740_64747",
        "score": 1
    },
    {
        "query_id": "740_202",
        "doc_id": "740_64902",
        "score": 1
    },
    {
        "query_id": "740_199",
        "doc_id": "740_65096",
        "score": 1
    },
    {
        "query_id": "740_721",
        "doc_id": "740_65428",
        "score": 1
    },
    {
        "query_id": "740_350",
        "doc_id": "740_65583",
        "score": 1
    },
    {
        "query_id": "740_206",
        "doc_id": "740_65668",
        "score": 1
    },
    {
        "query_id": "740_330",
        "doc_id": "740_65752",
        "score": 1
    },
    {
        "query_id": "740_434",
        "doc_id": "740_65761",
        "score": 1
    },
    {
        "query_id": "740_71",
        "doc_id": "740_65856",
        "score": 1
    },
    {
        "query_id": "740_86",
        "doc_id": "740_65891",
        "score": 1
    },
    {
        "query_id": "740_931",
        "doc_id": "740_66074",
        "score": 1
    },
    {
        "query_id": "740_888",
        "doc_id": "740_66087",
        "score": 1
    },
    {
        "query_id": "740_496",
        "doc_id": "740_66176",
        "score": 1
    },
    {
        "query_id": "740_528",
        "doc_id": "740_66264",
        "score": 1
    },
    {
        "query_id": "740_631",
        "doc_id": "740_66625",
        "score": 1
    },
    {
        "query_id": "740_643",
        "doc_id": "740_66981",
        "score": 1
    },
    {
        "query_id": "740_618",
        "doc_id": "740_66996",
        "score": 1
    },
    {
        "query_id": "740_269",
        "doc_id": "740_67302",
        "score": 1
    },
    {
        "query_id": "740_179",
        "doc_id": "740_67596",
        "score": 1
    },
    {
        "query_id": "740_343",
        "doc_id": "740_67622",
        "score": 1
    },
    {
        "query_id": "740_666",
        "doc_id": "740_67832",
        "score": 1
    },
    {
        "query_id": "740_596",
        "doc_id": "740_68036",
        "score": 1
    },
    {
        "query_id": "740_18",
        "doc_id": "740_68068",
        "score": 1
    },
    {
        "query_id": "740_782",
        "doc_id": "740_68091",
        "score": 1
    },
    {
        "query_id": "740_15",
        "doc_id": "740_68108",
        "score": 1
    },
    {
        "query_id": "740_348",
        "doc_id": "740_68196",
        "score": 1
    },
    {
        "query_id": "740_676",
        "doc_id": "740_68289",
        "score": 1
    },
    {
        "query_id": "740_770",
        "doc_id": "740_68309",
        "score": 1
    },
    {
        "query_id": "740_100",
        "doc_id": "740_68728",
        "score": 1
    },
    {
        "query_id": "740_130",
        "doc_id": "740_68906",
        "score": 1
    },
    {
        "query_id": "740_641",
        "doc_id": "740_69028",
        "score": 1
    },
    {
        "query_id": "740_58",
        "doc_id": "740_69059",
        "score": 1
    },
    {
        "query_id": "740_162",
        "doc_id": "740_69161",
        "score": 1
    },
    {
        "query_id": "740_447",
        "doc_id": "740_69507",
        "score": 1
    },
    {
        "query_id": "740_178",
        "doc_id": "740_69574",
        "score": 1
    },
    {
        "query_id": "740_64",
        "doc_id": "740_69617",
        "score": 1
    },
    {
        "query_id": "740_679",
        "doc_id": "740_69654",
        "score": 1
    },
    {
        "query_id": "740_771",
        "doc_id": "740_69728",
        "score": 1
    },
    {
        "query_id": "740_402",
        "doc_id": "740_69799",
        "score": 1
    },
    {
        "query_id": "740_735",
        "doc_id": "740_69838",
        "score": 1
    },
    {
        "query_id": "740_428",
        "doc_id": "740_69939",
        "score": 1
    },
    {
        "query_id": "740_338",
        "doc_id": "740_69978",
        "score": 1
    },
    {
        "query_id": "740_242",
        "doc_id": "740_69996",
        "score": 1
    },
    {
        "query_id": "740_539",
        "doc_id": "740_70233",
        "score": 1
    },
    {
        "query_id": "740_784",
        "doc_id": "740_70287",
        "score": 1
    },
    {
        "query_id": "740_887",
        "doc_id": "740_70572",
        "score": 1
    },
    {
        "query_id": "740_831",
        "doc_id": "740_70654",
        "score": 1
    },
    {
        "query_id": "740_384",
        "doc_id": "740_70670",
        "score": 1
    },
    {
        "query_id": "740_627",
        "doc_id": "740_70674",
        "score": 1
    },
    {
        "query_id": "740_624",
        "doc_id": "740_70870",
        "score": 1
    },
    {
        "query_id": "740_158",
        "doc_id": "740_70880",
        "score": 1
    },
    {
        "query_id": "740_741",
        "doc_id": "740_71382",
        "score": 1
    },
    {
        "query_id": "740_512",
        "doc_id": "740_71703",
        "score": 1
    },
    {
        "query_id": "740_353",
        "doc_id": "740_71808",
        "score": 1
    },
    {
        "query_id": "740_490",
        "doc_id": "740_71860",
        "score": 1
    },
    {
        "query_id": "740_304",
        "doc_id": "740_71941",
        "score": 1
    },
    {
        "query_id": "740_837",
        "doc_id": "740_71982",
        "score": 1
    },
    {
        "query_id": "740_440",
        "doc_id": "740_72050",
        "score": 1
    },
    {
        "query_id": "740_92",
        "doc_id": "740_72066",
        "score": 1
    },
    {
        "query_id": "740_120",
        "doc_id": "740_72353",
        "score": 1
    },
    {
        "query_id": "740_940",
        "doc_id": "740_72356",
        "score": 1
    },
    {
        "query_id": "740_229",
        "doc_id": "740_72455",
        "score": 1
    },
    {
        "query_id": "740_577",
        "doc_id": "740_72546",
        "score": 1
    },
    {
        "query_id": "740_695",
        "doc_id": "740_72706",
        "score": 1
    },
    {
        "query_id": "740_306",
        "doc_id": "740_72755",
        "score": 1
    },
    {
        "query_id": "740_855",
        "doc_id": "740_72854",
        "score": 1
    },
    {
        "query_id": "740_890",
        "doc_id": "740_72975",
        "score": 1
    },
    {
        "query_id": "740_115",
        "doc_id": "740_73126",
        "score": 1
    },
    {
        "query_id": "740_762",
        "doc_id": "740_73199",
        "score": 1
    },
    {
        "query_id": "740_302",
        "doc_id": "740_73289",
        "score": 1
    },
    {
        "query_id": "740_743",
        "doc_id": "740_73306",
        "score": 1
    },
    {
        "query_id": "740_755",
        "doc_id": "740_73310",
        "score": 1
    },
    {
        "query_id": "740_476",
        "doc_id": "740_73332",
        "score": 1
    },
    {
        "query_id": "740_450",
        "doc_id": "740_73423",
        "score": 1
    },
    {
        "query_id": "740_634",
        "doc_id": "740_73457",
        "score": 1
    },
    {
        "query_id": "740_710",
        "doc_id": "740_73792",
        "score": 1
    },
    {
        "query_id": "740_106",
        "doc_id": "740_73870",
        "score": 1
    },
    {
        "query_id": "740_122",
        "doc_id": "740_73973",
        "score": 1
    },
    {
        "query_id": "740_856",
        "doc_id": "740_74144",
        "score": 1
    },
    {
        "query_id": "740_357",
        "doc_id": "740_74217",
        "score": 1
    },
    {
        "query_id": "740_629",
        "doc_id": "740_74322",
        "score": 1
    },
    {
        "query_id": "740_885",
        "doc_id": "740_74355",
        "score": 1
    },
    {
        "query_id": "740_74",
        "doc_id": "740_74403",
        "score": 1
    },
    {
        "query_id": "740_922",
        "doc_id": "740_74457",
        "score": 1
    },
    {
        "query_id": "740_700",
        "doc_id": "740_74459",
        "score": 1
    },
    {
        "query_id": "740_535",
        "doc_id": "740_74642",
        "score": 1
    },
    {
        "query_id": "740_824",
        "doc_id": "740_74662",
        "score": 1
    },
    {
        "query_id": "740_801",
        "doc_id": "740_74673",
        "score": 1
    },
    {
        "query_id": "740_644",
        "doc_id": "740_74696",
        "score": 1
    },
    {
        "query_id": "740_409",
        "doc_id": "740_74721",
        "score": 1
    },
    {
        "query_id": "740_934",
        "doc_id": "740_74741",
        "score": 1
    },
    {
        "query_id": "740_567",
        "doc_id": "740_74759",
        "score": 1
    },
    {
        "query_id": "740_571",
        "doc_id": "740_74898",
        "score": 1
    },
    {
        "query_id": "740_40",
        "doc_id": "740_74964",
        "score": 1
    },
    {
        "query_id": "740_616",
        "doc_id": "740_74987",
        "score": 1
    },
    {
        "query_id": "740_558",
        "doc_id": "740_75145",
        "score": 1
    },
    {
        "query_id": "740_77",
        "doc_id": "740_75286",
        "score": 1
    },
    {
        "query_id": "740_198",
        "doc_id": "740_75483",
        "score": 1
    },
    {
        "query_id": "740_662",
        "doc_id": "740_75570",
        "score": 1
    },
    {
        "query_id": "740_720",
        "doc_id": "740_75752",
        "score": 1
    },
    {
        "query_id": "740_299",
        "doc_id": "740_75760",
        "score": 1
    },
    {
        "query_id": "740_19",
        "doc_id": "740_75902",
        "score": 1
    },
    {
        "query_id": "740_274",
        "doc_id": "740_75973",
        "score": 1
    },
    {
        "query_id": "740_97",
        "doc_id": "740_76054",
        "score": 1
    },
    {
        "query_id": "740_256",
        "doc_id": "740_76163",
        "score": 1
    },
    {
        "query_id": "740_335",
        "doc_id": "740_76204",
        "score": 1
    },
    {
        "query_id": "740_593",
        "doc_id": "740_76463",
        "score": 1
    },
    {
        "query_id": "740_781",
        "doc_id": "740_76643",
        "score": 1
    },
    {
        "query_id": "740_128",
        "doc_id": "740_76696",
        "score": 1
    },
    {
        "query_id": "740_32",
        "doc_id": "740_76990",
        "score": 1
    },
    {
        "query_id": "740_398",
        "doc_id": "740_77262",
        "score": 1
    },
    {
        "query_id": "740_285",
        "doc_id": "740_77279",
        "score": 1
    },
    {
        "query_id": "740_29",
        "doc_id": "740_77316",
        "score": 1
    },
    {
        "query_id": "740_851",
        "doc_id": "740_77581",
        "score": 1
    },
    {
        "query_id": "740_425",
        "doc_id": "740_77587",
        "score": 1
    },
    {
        "query_id": "740_760",
        "doc_id": "740_77609",
        "score": 1
    },
    {
        "query_id": "740_68",
        "doc_id": "740_77777",
        "score": 1
    },
    {
        "query_id": "740_2",
        "doc_id": "740_77930",
        "score": 1
    },
    {
        "query_id": "740_382",
        "doc_id": "740_77963",
        "score": 1
    },
    {
        "query_id": "740_254",
        "doc_id": "740_77991",
        "score": 1
    },
    {
        "query_id": "740_754",
        "doc_id": "740_78026",
        "score": 1
    },
    {
        "query_id": "740_396",
        "doc_id": "740_78146",
        "score": 1
    },
    {
        "query_id": "740_17",
        "doc_id": "740_78328",
        "score": 1
    },
    {
        "query_id": "740_843",
        "doc_id": "740_78572",
        "score": 1
    },
    {
        "query_id": "740_172",
        "doc_id": "740_78649",
        "score": 1
    },
    {
        "query_id": "740_793",
        "doc_id": "740_78714",
        "score": 1
    },
    {
        "query_id": "740_423",
        "doc_id": "740_78830",
        "score": 1
    },
    {
        "query_id": "740_389",
        "doc_id": "740_78929",
        "score": 1
    },
    {
        "query_id": "740_418",
        "doc_id": "740_79355",
        "score": 1
    },
    {
        "query_id": "740_714",
        "doc_id": "740_79370",
        "score": 1
    },
    {
        "query_id": "740_550",
        "doc_id": "740_79433",
        "score": 1
    },
    {
        "query_id": "740_717",
        "doc_id": "740_79507",
        "score": 1
    },
    {
        "query_id": "740_513",
        "doc_id": "740_79677",
        "score": 1
    },
    {
        "query_id": "740_578",
        "doc_id": "740_79688",
        "score": 1
    },
    {
        "query_id": "740_63",
        "doc_id": "740_79715",
        "score": 1
    },
    {
        "query_id": "740_758",
        "doc_id": "740_79720",
        "score": 1
    },
    {
        "query_id": "740_902",
        "doc_id": "740_79781",
        "score": 1
    },
    {
        "query_id": "740_862",
        "doc_id": "740_79832",
        "score": 1
    },
    {
        "query_id": "740_547",
        "doc_id": "740_79891",
        "score": 1
    },
    {
        "query_id": "740_288",
        "doc_id": "740_79951",
        "score": 1
    },
    {
        "query_id": "740_790",
        "doc_id": "740_80221",
        "score": 1
    },
    {
        "query_id": "740_757",
        "doc_id": "740_80301",
        "score": 1
    },
    {
        "query_id": "740_772",
        "doc_id": "740_80509",
        "score": 1
    },
    {
        "query_id": "740_112",
        "doc_id": "740_80550",
        "score": 1
    },
    {
        "query_id": "740_67",
        "doc_id": "740_80827",
        "score": 1
    },
    {
        "query_id": "740_445",
        "doc_id": "740_81018",
        "score": 1
    },
    {
        "query_id": "740_542",
        "doc_id": "740_81209",
        "score": 1
    },
    {
        "query_id": "740_192",
        "doc_id": "740_81235",
        "score": 1
    },
    {
        "query_id": "740_376",
        "doc_id": "740_81237",
        "score": 1
    },
    {
        "query_id": "740_272",
        "doc_id": "740_81252",
        "score": 1
    },
    {
        "query_id": "740_60",
        "doc_id": "740_81301",
        "score": 1
    },
    {
        "query_id": "740_759",
        "doc_id": "740_81391",
        "score": 1
    },
    {
        "query_id": "740_663",
        "doc_id": "740_81426",
        "score": 1
    },
    {
        "query_id": "740_448",
        "doc_id": "740_81690",
        "score": 1
    },
    {
        "query_id": "740_718",
        "doc_id": "740_81766",
        "score": 1
    },
    {
        "query_id": "740_725",
        "doc_id": "740_81897",
        "score": 1
    },
    {
        "query_id": "740_270",
        "doc_id": "740_82052",
        "score": 1
    },
    {
        "query_id": "740_687",
        "doc_id": "740_82135",
        "score": 1
    },
    {
        "query_id": "740_914",
        "doc_id": "740_82209",
        "score": 1
    },
    {
        "query_id": "740_719",
        "doc_id": "740_82406",
        "score": 1
    },
    {
        "query_id": "740_599",
        "doc_id": "740_82843",
        "score": 1
    },
    {
        "query_id": "740_69",
        "doc_id": "740_82845",
        "score": 1
    },
    {
        "query_id": "740_525",
        "doc_id": "740_82980",
        "score": 1
    },
    {
        "query_id": "740_613",
        "doc_id": "740_83089",
        "score": 1
    },
    {
        "query_id": "740_31",
        "doc_id": "740_83311",
        "score": 1
    },
    {
        "query_id": "740_817",
        "doc_id": "740_83344",
        "score": 1
    },
    {
        "query_id": "740_723",
        "doc_id": "740_83658",
        "score": 1
    },
    {
        "query_id": "740_866",
        "doc_id": "740_83802",
        "score": 1
    },
    {
        "query_id": "740_734",
        "doc_id": "740_83918",
        "score": 1
    },
    {
        "query_id": "740_377",
        "doc_id": "740_83965",
        "score": 1
    },
    {
        "query_id": "740_180",
        "doc_id": "740_83967",
        "score": 1
    },
    {
        "query_id": "740_456",
        "doc_id": "740_84383",
        "score": 1
    },
    {
        "query_id": "740_540",
        "doc_id": "740_84559",
        "score": 1
    },
    {
        "query_id": "740_121",
        "doc_id": "740_84565",
        "score": 1
    },
    {
        "query_id": "740_595",
        "doc_id": "740_84615",
        "score": 1
    },
    {
        "query_id": "740_569",
        "doc_id": "740_84709",
        "score": 1
    },
    {
        "query_id": "740_462",
        "doc_id": "740_84959",
        "score": 1
    },
    {
        "query_id": "740_287",
        "doc_id": "740_85111",
        "score": 1
    },
    {
        "query_id": "740_23",
        "doc_id": "740_85260",
        "score": 1
    },
    {
        "query_id": "740_827",
        "doc_id": "740_85341",
        "score": 1
    },
    {
        "query_id": "740_570",
        "doc_id": "740_85456",
        "score": 1
    },
    {
        "query_id": "740_930",
        "doc_id": "740_85613",
        "score": 1
    },
    {
        "query_id": "740_478",
        "doc_id": "740_85636",
        "score": 1
    },
    {
        "query_id": "740_818",
        "doc_id": "740_86012",
        "score": 1
    },
    {
        "query_id": "740_530",
        "doc_id": "740_86046",
        "score": 1
    },
    {
        "query_id": "740_938",
        "doc_id": "740_86146",
        "score": 1
    },
    {
        "query_id": "740_386",
        "doc_id": "740_86168",
        "score": 1
    },
    {
        "query_id": "740_495",
        "doc_id": "740_86416",
        "score": 1
    },
    {
        "query_id": "740_733",
        "doc_id": "740_86446",
        "score": 1
    },
    {
        "query_id": "740_188",
        "doc_id": "740_86474",
        "score": 1
    },
    {
        "query_id": "740_54",
        "doc_id": "740_86751",
        "score": 1
    },
    {
        "query_id": "740_473",
        "doc_id": "740_86944",
        "score": 1
    },
    {
        "query_id": "740_516",
        "doc_id": "740_86950",
        "score": 1
    },
    {
        "query_id": "740_580",
        "doc_id": "740_87306",
        "score": 1
    },
    {
        "query_id": "740_621",
        "doc_id": "740_87378",
        "score": 1
    },
    {
        "query_id": "740_466",
        "doc_id": "740_87507",
        "score": 1
    },
    {
        "query_id": "740_4",
        "doc_id": "740_87554",
        "score": 1
    },
    {
        "query_id": "740_668",
        "doc_id": "740_87665",
        "score": 1
    },
    {
        "query_id": "740_150",
        "doc_id": "740_87830",
        "score": 1
    },
    {
        "query_id": "740_919",
        "doc_id": "740_87839",
        "score": 1
    },
    {
        "query_id": "740_703",
        "doc_id": "740_87983",
        "score": 1
    },
    {
        "query_id": "740_91",
        "doc_id": "740_87998",
        "score": 1
    },
    {
        "query_id": "740_139",
        "doc_id": "740_88073",
        "score": 1
    },
    {
        "query_id": "740_152",
        "doc_id": "740_88184",
        "score": 1
    },
    {
        "query_id": "740_601",
        "doc_id": "740_88307",
        "score": 1
    },
    {
        "query_id": "740_529",
        "doc_id": "740_88360",
        "score": 1
    },
    {
        "query_id": "740_417",
        "doc_id": "740_88381",
        "score": 1
    },
    {
        "query_id": "740_119",
        "doc_id": "740_88516",
        "score": 1
    },
    {
        "query_id": "740_649",
        "doc_id": "740_88800",
        "score": 1
    },
    {
        "query_id": "740_181",
        "doc_id": "740_88818",
        "score": 1
    },
    {
        "query_id": "740_503",
        "doc_id": "740_88946",
        "score": 1
    },
    {
        "query_id": "740_11",
        "doc_id": "740_88985",
        "score": 1
    },
    {
        "query_id": "740_541",
        "doc_id": "740_89004",
        "score": 1
    },
    {
        "query_id": "740_924",
        "doc_id": "740_89220",
        "score": 1
    },
    {
        "query_id": "740_730",
        "doc_id": "740_89254",
        "score": 1
    },
    {
        "query_id": "740_253",
        "doc_id": "740_89285",
        "score": 1
    },
    {
        "query_id": "740_639",
        "doc_id": "740_89425",
        "score": 1
    },
    {
        "query_id": "740_83",
        "doc_id": "740_89426",
        "score": 1
    },
    {
        "query_id": "740_375",
        "doc_id": "740_89482",
        "score": 1
    },
    {
        "query_id": "740_141",
        "doc_id": "740_89591",
        "score": 1
    },
    {
        "query_id": "740_264",
        "doc_id": "740_89724",
        "score": 1
    },
    {
        "query_id": "740_401",
        "doc_id": "740_90015",
        "score": 1
    },
    {
        "query_id": "740_561",
        "doc_id": "740_90173",
        "score": 1
    },
    {
        "query_id": "740_413",
        "doc_id": "740_90198",
        "score": 1
    },
    {
        "query_id": "740_699",
        "doc_id": "740_90449",
        "score": 1
    },
    {
        "query_id": "740_135",
        "doc_id": "740_90513",
        "score": 1
    },
    {
        "query_id": "740_374",
        "doc_id": "740_90944",
        "score": 1
    },
    {
        "query_id": "740_42",
        "doc_id": "740_91120",
        "score": 1
    },
    {
        "query_id": "740_257",
        "doc_id": "740_91131",
        "score": 1
    },
    {
        "query_id": "740_142",
        "doc_id": "740_91199",
        "score": 1
    },
    {
        "query_id": "740_893",
        "doc_id": "740_91249",
        "score": 1
    },
    {
        "query_id": "740_391",
        "doc_id": "740_91387",
        "score": 1
    },
    {
        "query_id": "740_41",
        "doc_id": "740_91521",
        "score": 1
    },
    {
        "query_id": "740_249",
        "doc_id": "740_91595",
        "score": 1
    },
    {
        "query_id": "740_293",
        "doc_id": "740_91831",
        "score": 1
    },
    {
        "query_id": "740_103",
        "doc_id": "740_91866",
        "score": 1
    },
    {
        "query_id": "740_809",
        "doc_id": "740_91931",
        "score": 1
    },
    {
        "query_id": "740_268",
        "doc_id": "740_91971",
        "score": 1
    },
    {
        "query_id": "740_265",
        "doc_id": "740_92571",
        "score": 1
    },
    {
        "query_id": "740_806",
        "doc_id": "740_92645",
        "score": 1
    },
    {
        "query_id": "740_739",
        "doc_id": "740_92701",
        "score": 1
    },
    {
        "query_id": "740_796",
        "doc_id": "740_93036",
        "score": 1
    },
    {
        "query_id": "740_838",
        "doc_id": "740_93049",
        "score": 1
    },
    {
        "query_id": "740_164",
        "doc_id": "740_93107",
        "score": 1
    },
    {
        "query_id": "740_625",
        "doc_id": "740_93117",
        "score": 1
    },
    {
        "query_id": "740_438",
        "doc_id": "740_93154",
        "score": 1
    },
    {
        "query_id": "740_110",
        "doc_id": "740_93368",
        "score": 1
    },
    {
        "query_id": "740_813",
        "doc_id": "740_93578",
        "score": 1
    },
    {
        "query_id": "740_557",
        "doc_id": "740_93635",
        "score": 1
    },
    {
        "query_id": "740_439",
        "doc_id": "740_93673",
        "score": 1
    },
    {
        "query_id": "740_543",
        "doc_id": "740_93689",
        "score": 1
    },
    {
        "query_id": "740_514",
        "doc_id": "740_93864",
        "score": 1
    },
    {
        "query_id": "740_808",
        "doc_id": "740_94014",
        "score": 1
    },
    {
        "query_id": "740_368",
        "doc_id": "740_94222",
        "score": 1
    },
    {
        "query_id": "740_519",
        "doc_id": "740_94431",
        "score": 1
    },
    {
        "query_id": "740_795",
        "doc_id": "740_94435",
        "score": 1
    },
    {
        "query_id": "740_548",
        "doc_id": "740_94882",
        "score": 1
    },
    {
        "query_id": "740_575",
        "doc_id": "740_94905",
        "score": 1
    },
    {
        "query_id": "740_111",
        "doc_id": "740_94956",
        "score": 1
    },
    {
        "query_id": "740_537",
        "doc_id": "740_94998",
        "score": 1
    },
    {
        "query_id": "740_903",
        "doc_id": "740_95138",
        "score": 1
    },
    {
        "query_id": "740_523",
        "doc_id": "740_95144",
        "score": 1
    },
    {
        "query_id": "740_798",
        "doc_id": "740_95169",
        "score": 1
    },
    {
        "query_id": "740_491",
        "doc_id": "740_95296",
        "score": 1
    },
    {
        "query_id": "740_185",
        "doc_id": "740_95331",
        "score": 1
    },
    {
        "query_id": "740_395",
        "doc_id": "740_95428",
        "score": 1
    },
    {
        "query_id": "740_62",
        "doc_id": "740_95598",
        "score": 1
    },
    {
        "query_id": "740_408",
        "doc_id": "740_95653",
        "score": 1
    },
    {
        "query_id": "740_279",
        "doc_id": "740_95657",
        "score": 1
    },
    {
        "query_id": "740_576",
        "doc_id": "740_95755",
        "score": 1
    },
    {
        "query_id": "740_441",
        "doc_id": "740_95894",
        "score": 1
    },
    {
        "query_id": "740_499",
        "doc_id": "740_96010",
        "score": 1
    },
    {
        "query_id": "740_715",
        "doc_id": "740_96129",
        "score": 1
    },
    {
        "query_id": "740_488",
        "doc_id": "740_96144",
        "score": 1
    },
    {
        "query_id": "740_549",
        "doc_id": "740_96771",
        "score": 1
    },
    {
        "query_id": "740_773",
        "doc_id": "740_96967",
        "score": 1
    },
    {
        "query_id": "740_459",
        "doc_id": "740_97058",
        "score": 1
    },
    {
        "query_id": "740_78",
        "doc_id": "740_97063",
        "score": 1
    },
    {
        "query_id": "740_315",
        "doc_id": "740_97178",
        "score": 1
    },
    {
        "query_id": "740_295",
        "doc_id": "740_97400",
        "score": 1
    },
    {
        "query_id": "740_638",
        "doc_id": "740_97417",
        "score": 1
    },
    {
        "query_id": "740_589",
        "doc_id": "740_97642",
        "score": 1
    },
    {
        "query_id": "740_237",
        "doc_id": "740_97656",
        "score": 1
    },
    {
        "query_id": "740_836",
        "doc_id": "740_97681",
        "score": 1
    },
    {
        "query_id": "740_778",
        "doc_id": "740_97832",
        "score": 1
    },
    {
        "query_id": "740_191",
        "doc_id": "740_97870",
        "score": 1
    },
    {
        "query_id": "740_307",
        "doc_id": "740_98011",
        "score": 1
    },
    {
        "query_id": "740_109",
        "doc_id": "740_98266",
        "score": 1
    },
    {
        "query_id": "740_454",
        "doc_id": "740_98489",
        "score": 1
    },
    {
        "query_id": "740_840",
        "doc_id": "740_98583",
        "score": 1
    },
    {
        "query_id": "740_88",
        "doc_id": "740_98713",
        "score": 1
    },
    {
        "query_id": "740_1",
        "doc_id": "740_98742",
        "score": 1
    },
    {
        "query_id": "740_82",
        "doc_id": "740_98874",
        "score": 1
    },
    {
        "query_id": "740_892",
        "doc_id": "740_99025",
        "score": 1
    },
    {
        "query_id": "740_56",
        "doc_id": "740_99137",
        "score": 1
    },
    {
        "query_id": "740_551",
        "doc_id": "740_99301",
        "score": 1
    },
    {
        "query_id": "740_794",
        "doc_id": "740_99332",
        "score": 1
    },
    {
        "query_id": "740_22",
        "doc_id": "740_99377",
        "score": 1
    },
    {
        "query_id": "740_134",
        "doc_id": "740_99439",
        "score": 1
    },
    {
        "query_id": "740_99",
        "doc_id": "740_99565",
        "score": 1
    },
    {
        "query_id": "740_223",
        "doc_id": "740_99579",
        "score": 1
    },
    {
        "query_id": "740_564",
        "doc_id": "740_99582",
        "score": 1
    },
    {
        "query_id": "740_228",
        "doc_id": "740_99699",
        "score": 1
    },
    {
        "query_id": "740_705",
        "doc_id": "740_99780",
        "score": 1
    },
    {
        "query_id": "740_526",
        "doc_id": "740_99885",
        "score": 1
    },
    {
        "query_id": "740_362",
        "doc_id": "740_99995",
        "score": 1
    },
    {
        "query_id": "740_136",
        "doc_id": "740_100024",
        "score": 1
    },
    {
        "query_id": "740_511",
        "doc_id": "740_100095",
        "score": 1
    },
    {
        "query_id": "740_728",
        "doc_id": "740_100114",
        "score": 1
    },
    {
        "query_id": "740_608",
        "doc_id": "740_100145",
        "score": 1
    },
    {
        "query_id": "740_267",
        "doc_id": "740_100418",
        "score": 1
    },
    {
        "query_id": "740_874",
        "doc_id": "740_100473",
        "score": 1
    },
    {
        "query_id": "740_59",
        "doc_id": "740_100505",
        "score": 1
    },
    {
        "query_id": "740_591",
        "doc_id": "740_100597",
        "score": 1
    },
    {
        "query_id": "740_532",
        "doc_id": "740_100721",
        "score": 1
    },
    {
        "query_id": "740_10",
        "doc_id": "740_100856",
        "score": 1
    },
    {
        "query_id": "740_898",
        "doc_id": "740_100997",
        "score": 1
    },
    {
        "query_id": "740_296",
        "doc_id": "740_101077",
        "score": 1
    },
    {
        "query_id": "740_13",
        "doc_id": "740_101097",
        "score": 1
    },
    {
        "query_id": "740_905",
        "doc_id": "740_101262",
        "score": 1
    },
    {
        "query_id": "740_598",
        "doc_id": "740_101312",
        "score": 1
    },
    {
        "query_id": "740_672",
        "doc_id": "740_101716",
        "score": 1
    },
    {
        "query_id": "740_686",
        "doc_id": "740_101717",
        "score": 1
    },
    {
        "query_id": "740_776",
        "doc_id": "740_101807",
        "score": 1
    },
    {
        "query_id": "740_633",
        "doc_id": "740_101874",
        "score": 1
    },
    {
        "query_id": "740_870",
        "doc_id": "740_101989",
        "score": 1
    },
    {
        "query_id": "740_165",
        "doc_id": "740_102054",
        "score": 1
    },
    {
        "query_id": "740_505",
        "doc_id": "740_102094",
        "score": 1
    },
    {
        "query_id": "740_359",
        "doc_id": "740_102166",
        "score": 1
    },
    {
        "query_id": "740_645",
        "doc_id": "740_102317",
        "score": 1
    },
    {
        "query_id": "740_767",
        "doc_id": "740_102761",
        "score": 1
    },
    {
        "query_id": "740_255",
        "doc_id": "740_102783",
        "score": 1
    },
    {
        "query_id": "740_477",
        "doc_id": "740_102837",
        "score": 1
    },
    {
        "query_id": "740_792",
        "doc_id": "740_102873",
        "score": 1
    },
    {
        "query_id": "740_221",
        "doc_id": "740_103103",
        "score": 1
    },
    {
        "query_id": "740_116",
        "doc_id": "740_103135",
        "score": 1
    },
    {
        "query_id": "740_147",
        "doc_id": "740_103246",
        "score": 1
    },
    {
        "query_id": "740_196",
        "doc_id": "740_103272",
        "score": 1
    },
    {
        "query_id": "740_786",
        "doc_id": "740_103303",
        "score": 1
    },
    {
        "query_id": "740_259",
        "doc_id": "740_103369",
        "score": 1
    },
    {
        "query_id": "740_414",
        "doc_id": "740_103370",
        "score": 1
    },
    {
        "query_id": "740_197",
        "doc_id": "740_103475",
        "score": 1
    },
    {
        "query_id": "740_536",
        "doc_id": "740_103484",
        "score": 1
    },
    {
        "query_id": "740_545",
        "doc_id": "740_103615",
        "score": 1
    },
    {
        "query_id": "740_895",
        "doc_id": "740_103748",
        "score": 1
    },
    {
        "query_id": "740_276",
        "doc_id": "740_103767",
        "score": 1
    },
    {
        "query_id": "740_807",
        "doc_id": "740_103899",
        "score": 1
    },
    {
        "query_id": "740_697",
        "doc_id": "740_103945",
        "score": 1
    },
    {
        "query_id": "740_30",
        "doc_id": "740_104091",
        "score": 1
    },
    {
        "query_id": "740_615",
        "doc_id": "740_104193",
        "score": 1
    },
    {
        "query_id": "740_775",
        "doc_id": "740_104281",
        "score": 1
    },
    {
        "query_id": "740_820",
        "doc_id": "740_104300",
        "score": 1
    },
    {
        "query_id": "740_200",
        "doc_id": "740_104305",
        "score": 1
    },
    {
        "query_id": "740_403",
        "doc_id": "740_104348",
        "score": 1
    },
    {
        "query_id": "740_916",
        "doc_id": "740_104375",
        "score": 1
    },
    {
        "query_id": "740_785",
        "doc_id": "740_104382",
        "score": 1
    },
    {
        "query_id": "740_685",
        "doc_id": "740_104391",
        "score": 1
    },
    {
        "query_id": "740_479",
        "doc_id": "740_104401",
        "score": 1
    },
    {
        "query_id": "740_319",
        "doc_id": "740_104491",
        "score": 1
    },
    {
        "query_id": "740_166",
        "doc_id": "740_104503",
        "score": 1
    },
    {
        "query_id": "740_839",
        "doc_id": "740_104689",
        "score": 1
    },
    {
        "query_id": "740_588",
        "doc_id": "740_104707",
        "score": 1
    },
    {
        "query_id": "740_677",
        "doc_id": "740_104806",
        "score": 1
    },
    {
        "query_id": "740_422",
        "doc_id": "740_104838",
        "score": 1
    },
    {
        "query_id": "740_212",
        "doc_id": "740_105047",
        "score": 1
    },
    {
        "query_id": "740_431",
        "doc_id": "740_105076",
        "score": 1
    },
    {
        "query_id": "740_155",
        "doc_id": "740_105185",
        "score": 1
    },
    {
        "query_id": "740_494",
        "doc_id": "740_105242",
        "score": 1
    },
    {
        "query_id": "740_352",
        "doc_id": "740_105407",
        "score": 1
    },
    {
        "query_id": "740_670",
        "doc_id": "740_105426",
        "score": 1
    },
    {
        "query_id": "740_816",
        "doc_id": "740_105448",
        "score": 1
    },
    {
        "query_id": "740_582",
        "doc_id": "740_105533",
        "score": 1
    },
    {
        "query_id": "740_501",
        "doc_id": "740_105676",
        "score": 1
    },
    {
        "query_id": "740_659",
        "doc_id": "740_105684",
        "score": 1
    },
    {
        "query_id": "740_203",
        "doc_id": "740_106065",
        "score": 1
    },
    {
        "query_id": "740_711",
        "doc_id": "740_106231",
        "score": 1
    },
    {
        "query_id": "740_455",
        "doc_id": "740_106648",
        "score": 1
    },
    {
        "query_id": "740_889",
        "doc_id": "740_106699",
        "score": 1
    },
    {
        "query_id": "740_337",
        "doc_id": "740_106843",
        "score": 1
    },
    {
        "query_id": "740_429",
        "doc_id": "740_106937",
        "score": 1
    },
    {
        "query_id": "740_412",
        "doc_id": "740_107138",
        "score": 1
    },
    {
        "query_id": "740_753",
        "doc_id": "740_107176",
        "score": 1
    },
    {
        "query_id": "740_766",
        "doc_id": "740_107663",
        "score": 1
    },
    {
        "query_id": "740_805",
        "doc_id": "740_108438",
        "score": 1
    },
    {
        "query_id": "740_504",
        "doc_id": "740_108523",
        "score": 1
    },
    {
        "query_id": "740_394",
        "doc_id": "740_108617",
        "score": 1
    },
    {
        "query_id": "740_632",
        "doc_id": "740_108715",
        "score": 1
    },
    {
        "query_id": "740_706",
        "doc_id": "740_108719",
        "score": 1
    },
    {
        "query_id": "740_458",
        "doc_id": "740_108796",
        "score": 1
    },
    {
        "query_id": "740_533",
        "doc_id": "740_108895",
        "score": 1
    },
    {
        "query_id": "740_205",
        "doc_id": "740_109000",
        "score": 1
    },
    {
        "query_id": "740_803",
        "doc_id": "740_109011",
        "score": 1
    },
    {
        "query_id": "740_912",
        "doc_id": "740_109106",
        "score": 1
    },
    {
        "query_id": "740_193",
        "doc_id": "740_109180",
        "score": 1
    },
    {
        "query_id": "740_713",
        "doc_id": "740_109269",
        "score": 1
    },
    {
        "query_id": "740_732",
        "doc_id": "740_109300",
        "score": 1
    },
    {
        "query_id": "740_872",
        "doc_id": "740_109421",
        "score": 1
    },
    {
        "query_id": "740_327",
        "doc_id": "740_109665",
        "score": 1
    },
    {
        "query_id": "740_75",
        "doc_id": "740_109702",
        "score": 1
    },
    {
        "query_id": "740_230",
        "doc_id": "740_109731",
        "score": 1
    },
    {
        "query_id": "740_853",
        "doc_id": "740_109803",
        "score": 1
    },
    {
        "query_id": "740_729",
        "doc_id": "740_109859",
        "score": 1
    },
    {
        "query_id": "740_190",
        "doc_id": "740_110092",
        "score": 1
    },
    {
        "query_id": "740_568",
        "doc_id": "740_110539",
        "score": 1
    },
    {
        "query_id": "740_811",
        "doc_id": "740_110553",
        "score": 1
    },
    {
        "query_id": "740_752",
        "doc_id": "740_110598",
        "score": 1
    },
    {
        "query_id": "740_95",
        "doc_id": "740_110611",
        "score": 1
    },
    {
        "query_id": "740_404",
        "doc_id": "740_110674",
        "score": 1
    },
    {
        "query_id": "740_906",
        "doc_id": "740_110720",
        "score": 1
    },
    {
        "query_id": "740_290",
        "doc_id": "740_110767",
        "score": 1
    },
    {
        "query_id": "740_157",
        "doc_id": "740_110787",
        "score": 1
    },
    {
        "query_id": "740_859",
        "doc_id": "740_110826",
        "score": 1
    },
    {
        "query_id": "740_231",
        "doc_id": "740_110829",
        "score": 1
    },
    {
        "query_id": "740_546",
        "doc_id": "740_110861",
        "score": 1
    },
    {
        "query_id": "740_104",
        "doc_id": "740_110892",
        "score": 1
    },
    {
        "query_id": "740_814",
        "doc_id": "740_110954",
        "score": 1
    },
    {
        "query_id": "740_849",
        "doc_id": "740_111059",
        "score": 1
    },
    {
        "query_id": "740_321",
        "doc_id": "740_111090",
        "score": 1
    },
    {
        "query_id": "740_12",
        "doc_id": "740_111137",
        "score": 1
    },
    {
        "query_id": "740_744",
        "doc_id": "740_111210",
        "score": 1
    },
    {
        "query_id": "740_201",
        "doc_id": "740_111232",
        "score": 1
    },
    {
        "query_id": "740_740",
        "doc_id": "740_111396",
        "score": 1
    },
    {
        "query_id": "740_789",
        "doc_id": "740_111423",
        "score": 1
    },
    {
        "query_id": "740_443",
        "doc_id": "740_111671",
        "score": 1
    },
    {
        "query_id": "740_907",
        "doc_id": "740_111878",
        "score": 1
    },
    {
        "query_id": "740_236",
        "doc_id": "740_112009",
        "score": 1
    },
    {
        "query_id": "740_614",
        "doc_id": "740_112136",
        "score": 1
    },
    {
        "query_id": "740_46",
        "doc_id": "740_112254",
        "score": 1
    },
    {
        "query_id": "740_656",
        "doc_id": "740_112297",
        "score": 1
    },
    {
        "query_id": "740_896",
        "doc_id": "740_112351",
        "score": 1
    },
    {
        "query_id": "740_5",
        "doc_id": "740_112587",
        "score": 1
    },
    {
        "query_id": "740_204",
        "doc_id": "740_112591",
        "score": 1
    },
    {
        "query_id": "740_474",
        "doc_id": "740_112602",
        "score": 1
    },
    {
        "query_id": "740_137",
        "doc_id": "740_112741",
        "score": 1
    },
    {
        "query_id": "740_318",
        "doc_id": "740_112865",
        "score": 1
    },
    {
        "query_id": "740_177",
        "doc_id": "740_112971",
        "score": 1
    },
    {
        "query_id": "740_600",
        "doc_id": "740_113083",
        "score": 1
    },
    {
        "query_id": "740_273",
        "doc_id": "740_113267",
        "score": 1
    },
    {
        "query_id": "740_328",
        "doc_id": "740_113325",
        "score": 1
    },
    {
        "query_id": "740_704",
        "doc_id": "740_113363",
        "score": 1
    },
    {
        "query_id": "740_339",
        "doc_id": "740_113375",
        "score": 1
    },
    {
        "query_id": "740_747",
        "doc_id": "740_113440",
        "score": 1
    },
    {
        "query_id": "740_380",
        "doc_id": "740_113509",
        "score": 1
    },
    {
        "query_id": "740_449",
        "doc_id": "740_113603",
        "score": 1
    },
    {
        "query_id": "740_480",
        "doc_id": "740_113897",
        "score": 1
    },
    {
        "query_id": "740_250",
        "doc_id": "740_113925",
        "score": 1
    },
    {
        "query_id": "740_248",
        "doc_id": "740_113970",
        "score": 1
    },
    {
        "query_id": "740_241",
        "doc_id": "740_114005",
        "score": 1
    },
    {
        "query_id": "740_653",
        "doc_id": "740_114042",
        "score": 1
    },
    {
        "query_id": "740_400",
        "doc_id": "740_114150",
        "score": 1
    },
    {
        "query_id": "740_222",
        "doc_id": "740_114220",
        "score": 1
    },
    {
        "query_id": "740_857",
        "doc_id": "740_114384",
        "score": 1
    },
    {
        "query_id": "740_815",
        "doc_id": "740_114859",
        "score": 1
    },
    {
        "query_id": "740_834",
        "doc_id": "740_114870",
        "score": 1
    },
    {
        "query_id": "740_27",
        "doc_id": "740_114988",
        "score": 1
    },
    {
        "query_id": "740_277",
        "doc_id": "740_115077",
        "score": 1
    },
    {
        "query_id": "740_153",
        "doc_id": "740_115143",
        "score": 1
    },
    {
        "query_id": "740_320",
        "doc_id": "740_115153",
        "score": 1
    },
    {
        "query_id": "740_246",
        "doc_id": "740_115187",
        "score": 1
    },
    {
        "query_id": "740_873",
        "doc_id": "740_115242",
        "score": 1
    },
    {
        "query_id": "740_660",
        "doc_id": "740_115355",
        "score": 1
    },
    {
        "query_id": "740_489",
        "doc_id": "740_115391",
        "score": 1
    },
    {
        "query_id": "740_340",
        "doc_id": "740_115417",
        "score": 1
    },
    {
        "query_id": "740_869",
        "doc_id": "740_115491",
        "score": 1
    },
    {
        "query_id": "740_369",
        "doc_id": "740_115568",
        "score": 1
    },
    {
        "query_id": "740_433",
        "doc_id": "740_115623",
        "score": 1
    },
    {
        "query_id": "740_84",
        "doc_id": "740_115794",
        "score": 1
    },
    {
        "query_id": "740_684",
        "doc_id": "740_115950",
        "score": 1
    },
    {
        "query_id": "740_303",
        "doc_id": "740_115998",
        "score": 1
    },
    {
        "query_id": "740_436",
        "doc_id": "740_116012",
        "score": 1
    },
    {
        "query_id": "740_524",
        "doc_id": "740_116088",
        "score": 1
    },
    {
        "query_id": "740_208",
        "doc_id": "740_116089",
        "score": 1
    },
    {
        "query_id": "740_305",
        "doc_id": "740_116178",
        "score": 1
    },
    {
        "query_id": "740_309",
        "doc_id": "740_116318",
        "score": 1
    },
    {
        "query_id": "740_43",
        "doc_id": "740_116429",
        "score": 1
    },
    {
        "query_id": "740_184",
        "doc_id": "740_116446",
        "score": 1
    },
    {
        "query_id": "740_563",
        "doc_id": "740_116557",
        "score": 1
    },
    {
        "query_id": "740_681",
        "doc_id": "740_116638",
        "score": 1
    },
    {
        "query_id": "740_361",
        "doc_id": "740_116720",
        "score": 1
    },
    {
        "query_id": "740_251",
        "doc_id": "740_116741",
        "score": 1
    },
    {
        "query_id": "740_928",
        "doc_id": "740_116781",
        "score": 1
    },
    {
        "query_id": "740_407",
        "doc_id": "740_116788",
        "score": 1
    },
    {
        "query_id": "740_748",
        "doc_id": "740_116833",
        "score": 1
    },
    {
        "query_id": "740_867",
        "doc_id": "740_117025",
        "score": 1
    },
    {
        "query_id": "740_584",
        "doc_id": "740_117095",
        "score": 1
    },
    {
        "query_id": "740_209",
        "doc_id": "740_117235",
        "score": 1
    },
    {
        "query_id": "740_603",
        "doc_id": "740_117275",
        "score": 1
    },
    {
        "query_id": "740_406",
        "doc_id": "740_117285",
        "score": 1
    },
    {
        "query_id": "740_346",
        "doc_id": "740_117347",
        "score": 1
    },
    {
        "query_id": "740_355",
        "doc_id": "740_117357",
        "score": 1
    },
    {
        "query_id": "740_57",
        "doc_id": "740_117365",
        "score": 1
    },
    {
        "query_id": "740_572",
        "doc_id": "740_117450",
        "score": 1
    },
    {
        "query_id": "740_151",
        "doc_id": "740_117497",
        "score": 1
    },
    {
        "query_id": "740_749",
        "doc_id": "740_117676",
        "score": 1
    },
    {
        "query_id": "740_583",
        "doc_id": "740_117735",
        "score": 1
    },
    {
        "query_id": "740_521",
        "doc_id": "740_117750",
        "score": 1
    },
    {
        "query_id": "740_829",
        "doc_id": "740_117753",
        "score": 1
    },
    {
        "query_id": "740_675",
        "doc_id": "740_117907",
        "score": 1
    },
    {
        "query_id": "740_215",
        "doc_id": "740_118245",
        "score": 1
    },
    {
        "query_id": "740_347",
        "doc_id": "740_118257",
        "score": 1
    },
    {
        "query_id": "740_585",
        "doc_id": "740_118474",
        "score": 1
    },
    {
        "query_id": "740_144",
        "doc_id": "740_118483",
        "score": 1
    },
    {
        "query_id": "740_3",
        "doc_id": "740_118504",
        "score": 1
    },
    {
        "query_id": "740_387",
        "doc_id": "740_118541",
        "score": 1
    },
    {
        "query_id": "740_154",
        "doc_id": "740_118635",
        "score": 1
    },
    {
        "query_id": "740_410",
        "doc_id": "740_118711",
        "score": 1
    },
    {
        "query_id": "740_182",
        "doc_id": "740_118734",
        "score": 1
    },
    {
        "query_id": "740_421",
        "doc_id": "740_118748",
        "score": 1
    },
    {
        "query_id": "740_554",
        "doc_id": "740_118767",
        "score": 1
    },
    {
        "query_id": "740_324",
        "doc_id": "740_118769",
        "score": 1
    },
    {
        "query_id": "740_941",
        "doc_id": "740_118800",
        "score": 1
    },
    {
        "query_id": "740_844",
        "doc_id": "740_118913",
        "score": 1
    },
    {
        "query_id": "740_868",
        "doc_id": "740_118922",
        "score": 1
    },
    {
        "query_id": "740_647",
        "doc_id": "740_118945",
        "score": 1
    },
    {
        "query_id": "740_586",
        "doc_id": "740_119021",
        "score": 1
    },
    {
        "query_id": "740_482",
        "doc_id": "740_119025",
        "score": 1
    },
    {
        "query_id": "740_127",
        "doc_id": "740_119035",
        "score": 1
    },
    {
        "query_id": "740_750",
        "doc_id": "740_119049",
        "score": 1
    },
    {
        "query_id": "740_506",
        "doc_id": "740_119106",
        "score": 1
    },
    {
        "query_id": "740_73",
        "doc_id": "740_119572",
        "score": 1
    },
    {
        "query_id": "740_378",
        "doc_id": "740_119633",
        "score": 1
    },
    {
        "query_id": "740_707",
        "doc_id": "740_119649",
        "score": 1
    },
    {
        "query_id": "740_37",
        "doc_id": "740_119692",
        "score": 1
    },
    {
        "query_id": "740_419",
        "doc_id": "740_119716",
        "score": 1
    },
    {
        "query_id": "740_774",
        "doc_id": "740_119722",
        "score": 1
    },
    {
        "query_id": "740_20",
        "doc_id": "740_119948",
        "score": 1
    },
    {
        "query_id": "740_590",
        "doc_id": "740_119958",
        "score": 1
    },
    {
        "query_id": "740_143",
        "doc_id": "740_119966",
        "score": 1
    },
    {
        "query_id": "740_877",
        "doc_id": "740_120188",
        "score": 1
    },
    {
        "query_id": "740_661",
        "doc_id": "740_120322",
        "score": 1
    },
    {
        "query_id": "740_628",
        "doc_id": "740_120331",
        "score": 1
    },
    {
        "query_id": "740_852",
        "doc_id": "740_120467",
        "score": 1
    },
    {
        "query_id": "740_392",
        "doc_id": "740_120597",
        "score": 1
    },
    {
        "query_id": "740_220",
        "doc_id": "740_120598",
        "score": 1
    },
    {
        "query_id": "740_349",
        "doc_id": "740_120645",
        "score": 1
    },
    {
        "query_id": "740_858",
        "doc_id": "740_120665",
        "score": 1
    },
    {
        "query_id": "740_370",
        "doc_id": "740_120916",
        "score": 1
    },
    {
        "query_id": "740_832",
        "doc_id": "740_121270",
        "score": 1
    },
    {
        "query_id": "740_556",
        "doc_id": "740_121291",
        "score": 1
    },
    {
        "query_id": "740_664",
        "doc_id": "740_121347",
        "score": 1
    },
    {
        "query_id": "740_283",
        "doc_id": "740_121435",
        "score": 1
    },
    {
        "query_id": "740_294",
        "doc_id": "740_121513",
        "score": 1
    },
    {
        "query_id": "740_609",
        "doc_id": "740_121570",
        "score": 1
    },
    {
        "query_id": "740_364",
        "doc_id": "740_121628",
        "score": 1
    },
    {
        "query_id": "740_652",
        "doc_id": "740_121689",
        "score": 1
    },
    {
        "query_id": "740_291",
        "doc_id": "740_121838",
        "score": 1
    },
    {
        "query_id": "740_105",
        "doc_id": "740_121881",
        "score": 1
    },
    {
        "query_id": "740_654",
        "doc_id": "740_121896",
        "score": 1
    },
    {
        "query_id": "740_214",
        "doc_id": "740_121937",
        "score": 1
    },
    {
        "query_id": "740_28",
        "doc_id": "740_121978",
        "score": 1
    },
    {
        "query_id": "740_16",
        "doc_id": "740_121988",
        "score": 1
    },
    {
        "query_id": "740_464",
        "doc_id": "740_122004",
        "score": 1
    },
    {
        "query_id": "740_791",
        "doc_id": "740_122079",
        "score": 1
    },
    {
        "query_id": "740_415",
        "doc_id": "740_122173",
        "score": 1
    },
    {
        "query_id": "740_354",
        "doc_id": "740_122205",
        "score": 1
    },
    {
        "query_id": "740_26",
        "doc_id": "740_122307",
        "score": 1
    },
    {
        "query_id": "740_217",
        "doc_id": "740_122357",
        "score": 1
    },
    {
        "query_id": "740_854",
        "doc_id": "740_122531",
        "score": 1
    },
    {
        "query_id": "740_544",
        "doc_id": "740_122646",
        "score": 1
    },
    {
        "query_id": "740_901",
        "doc_id": "740_122649",
        "score": 1
    },
    {
        "query_id": "740_636",
        "doc_id": "740_122715",
        "score": 1
    },
    {
        "query_id": "740_777",
        "doc_id": "740_122906",
        "score": 1
    },
    {
        "query_id": "740_724",
        "doc_id": "740_123013",
        "score": 1
    },
    {
        "query_id": "740_38",
        "doc_id": "740_123062",
        "score": 1
    },
    {
        "query_id": "740_176",
        "doc_id": "740_123092",
        "score": 1
    },
    {
        "query_id": "740_298",
        "doc_id": "740_123238",
        "score": 1
    },
    {
        "query_id": "740_76",
        "doc_id": "740_123307",
        "score": 1
    },
    {
        "query_id": "740_487",
        "doc_id": "740_123377",
        "score": 1
    },
    {
        "query_id": "740_234",
        "doc_id": "740_123443",
        "score": 1
    },
    {
        "query_id": "740_9",
        "doc_id": "740_123453",
        "score": 1
    },
    {
        "query_id": "740_500",
        "doc_id": "740_123545",
        "score": 1
    },
    {
        "query_id": "740_821",
        "doc_id": "740_123704",
        "score": 1
    },
    {
        "query_id": "740_899",
        "doc_id": "740_123850",
        "score": 1
    },
    {
        "query_id": "740_565",
        "doc_id": "740_123945",
        "score": 1
    },
    {
        "query_id": "740_261",
        "doc_id": "740_123953",
        "score": 1
    },
    {
        "query_id": "740_461",
        "doc_id": "740_124041",
        "score": 1
    },
    {
        "query_id": "740_437",
        "doc_id": "740_124060",
        "score": 1
    },
    {
        "query_id": "740_211",
        "doc_id": "740_124256",
        "score": 1
    },
    {
        "query_id": "740_657",
        "doc_id": "740_124294",
        "score": 1
    },
    {
        "query_id": "740_606",
        "doc_id": "740_124299",
        "score": 1
    }
]